cloudnode/__init__.py
cloudnode/app_harder.py
cloudnode/config.py
cloudnode/base/__init__.py
cloudnode/base/core/__init__.py
cloudnode/base/core/elasticsearch/__init__.py
cloudnode/base/core/elasticsearch/search.py
cloudnode/base/core/lightweight_utilities/__init__.py
cloudnode/base/core/lightweight_utilities/cloudnode.py
cloudnode/base/core/lightweight_utilities/dicts.py
cloudnode/base/core/lightweight_utilities/files.py
cloudnode/base/core/lightweight_utilities/filesystem.py
cloudnode/base/core/lightweight_utilities/misc.py
cloudnode/base/core/lightweight_utilities/misc_logging.py
cloudnode/base/core/lightweight_utilities/parallel.py
cloudnode/base/core/lightweight_utilities/profiler_logger.py
cloudnode/base/core/lightweight_utilities/sysops.py
cloudnode/base/core/swiftdata/__init__.py
cloudnode/base/core/swiftdata/modeling.py
cloudnode/base/core/swiftdata/models.py
cloudnode/base/core/thirdparty/DockerClient.py
cloudnode/base/core/thirdparty/__init__.py
cloudnode/base/iaas/CloudNodeLogger.py
cloudnode/base/iaas/__init__.py
cloudnode/base/iaas/aether.py
cloudnode/base/iaas/client.py
cloudnode/base/iaas/cron.py
cloudnode/base/iaas/files.py
cloudnode/base/iaas/for_functions.py
cloudnode/base/iaas/nodes/BuildServletConfig.py
cloudnode/base/iaas/nodes/Infrastructure.py
cloudnode/base/iaas/nodes/TraditionalCloudFunction.py
cloudnode/base/iaas/nodes/__init__.py
cloudnode/base/iaas/nodes/thirdparty/ShinyServlet.py
cloudnode/base/iaas/nodes/thirdparty/__init__.py
cloudnode/functions/__init__.py
cloudnode/functions/admin.py
cloudnode-2024.9.1.dist-info/LICENSE
cloudnode-2024.9.1.dist-info/METADATA
cloudnode-2024.9.1.dist-info/WHEEL
cloudnode-2024.9.1.dist-info/top_level.txt
cloudnode-2024.9.1.dist-info/RECORD
