Metadata-Version: 2.1
Name: cloudnode
Version: 2024.9.1
Summary: cloudnode is for building apps on home servers.
Author-email: Starlight <david@starlight.ai>
Maintainer-email: Starlight <david@starlight.ai>
Project-URL: Homepage, https://github.com/markelwin/CloudNode
Project-URL: Repository, https://github.com/markelwin/CloudNode.git
Project-URL: Issues, https://github.com/markelwin/CloudNode/issues
Keywords: cloudnode,infrastructure,engineering,search,home,machine learning
Classifier: Development Status :: 4 - Beta
Classifier: Programming Language :: Python :: 3
Classifier: License :: OSI Approved :: GNU General Public License v3 (GPLv3)
Classifier: Operating System :: OS Independent
Requires-Python: >=3.8
License-File: LICENSE
Requires-Dist: python-magic
Requires-Dist: dateparser
Requires-Dist: pyyaml
Requires-Dist: elasticsearch
Requires-Dist: elasticsearch-dsl
Requires-Dist: pandas
Requires-Dist: docker
Requires-Dist: flask
Requires-Dist: flask-RESTful
Requires-Dist: flask-cors
Requires-Dist: requests
Requires-Dist: shiny
